Metadata-Version: 2.1
Name: auth-gosuslugi
Version: 0.0.3
Summary: Authorization on sites through gosuslugi using requests.
Home-page: https://github.com/daniilak/auth-gosuslugi
Author: Daniil Agniashvili
Author-email: dortos123456@gmail.com
Classifier: Programming Language :: Python :: 3
Classifier: License :: OSI Approved :: MIT License
Classifier: Operating System :: Microsoft :: Windows
Classifier: Operating System :: POSIX :: Linux
Requires-Python: >3.5
License-File: LICENCE.txt
